gpt_docs_and_tests/__init__.py
gpt_docs_and_tests/__main__.py
gpt_docs_and_tests/adder.py
gpt_docs_and_tests-0.0.7.dist-info/METADATA
gpt_docs_and_tests-0.0.7.dist-info/WHEEL
gpt_docs_and_tests-0.0.7.dist-info/entry_points.txt
gpt_docs_and_tests-0.0.7.dist-info/top_level.txt
gpt_docs_and_tests-0.0.7.dist-info/RECORD
